[
    {
        "sandbox_name": "Before After",
        "sandbox_desc": "Use HTML, CSS, JS native",
        "sandbox_img_url": "sandbox-menu/images/sandbox_01.jpg"
    },
    {
        "sandbox_name": "Parallax Orbs",
        "sandbox_desc": "Use HTML, CSS",
        "sandbox_img_url": "sandbox-menu/images/sandbox_02.jpg"
    },
    {
        "sandbox_name": "null",
        "sandbox_desc": "Use HTML, CSS",
        "sandbox_img_url": "sandbox-menu/images/sandbox_03.jpg"
    },
    {
        "sandbox_name": "null",
        "sandbox_desc": "Use HTML, CSS",
        "sandbox_img_url": "sandbox-menu/images/sandbox_03.jpg"
    }
]